airflow_operators/__init__.py
airflow_operators/elastic.py
airflow_operators/kafka.py
airflow_operators/sqlaclhemy.py
airflow_operators/sqlalchemy.py
airflow_operators/utils/__init__.py
airflow_operators/utils/importer.py
airflow_operators/utils/orm_converter.py
airflow_operators/utils/redis.py
airflow_operators-0.16.0.dist-info/METADATA
airflow_operators-0.16.0.dist-info/WHEEL
airflow_operators-0.16.0.dist-info/RECORD
